dyconnmap/__init__.py
dyconnmap/analytic_signal.py
dyconnmap/bands.py
dyconnmap/sliding_window.py
dyconnmap/tvfcgs.py
dyconnmap/chronnectomics/__init__.py
dyconnmap/chronnectomics/dwell_time.py
dyconnmap/chronnectomics/flexibility_index.py
dyconnmap/chronnectomics/occupancy_time.py
dyconnmap/cluster/__init__.py
dyconnmap/cluster/cluster.py
dyconnmap/cluster/gng.py
dyconnmap/cluster/mng.py
dyconnmap/cluster/ng.py
dyconnmap/cluster/rng.py
dyconnmap/cluster/som.py
dyconnmap/cluster/umatrix.py
dyconnmap/cluster/validity.py
dyconnmap/fc/__init__.py
dyconnmap/fc/aec.py
dyconnmap/fc/biplv.py
dyconnmap/fc/coherence.py
dyconnmap/fc/corr.py
dyconnmap/fc/cos.py
dyconnmap/fc/crosscorr.py
dyconnmap/fc/dpli.py
dyconnmap/fc/esc.py
dyconnmap/fc/estimator.py
dyconnmap/fc/glm.py
dyconnmap/fc/icoherence.py
dyconnmap/fc/iplv.py
dyconnmap/fc/mui.py
dyconnmap/fc/nesc.py
dyconnmap/fc/pac.py
dyconnmap/fc/partcorr.py
dyconnmap/fc/pec.py
dyconnmap/fc/pli.py
dyconnmap/fc/plv.py
dyconnmap/fc/rho_index.py
dyconnmap/fc/wpli.py
dyconnmap/graphs/__init__.py
dyconnmap/graphs/e2e.py
dyconnmap/graphs/gdd.py
dyconnmap/graphs/imd.py
dyconnmap/graphs/laplacian_energy.py
dyconnmap/graphs/mi.py
dyconnmap/graphs/mpc.py
dyconnmap/graphs/nodal.py
dyconnmap/graphs/spectral_euclidean_distance.py
dyconnmap/graphs/spectral_k_distance.py
dyconnmap/graphs/threshold.py
dyconnmap/graphs/vi.py
dyconnmap/sim_models/__init__.py
dyconnmap/sim_models/makinen.py
dyconnmap/ts/__init__.py
dyconnmap/ts/ci.py
dyconnmap/ts/cv.py
dyconnmap/ts/dcorr.py
dyconnmap/ts/embed_delay.py
dyconnmap/ts/entropy.py
dyconnmap/ts/fisher_score.py
dyconnmap/ts/fisher_z.py
dyconnmap/ts/fnn.py
dyconnmap/ts/icc.py
dyconnmap/ts/markov_matrix.py
dyconnmap/ts/ordinal_pattern_similarity.py
dyconnmap/ts/permutation_entropy.py
dyconnmap/ts/rr_order_patterns.py
dyconnmap/ts/sampen.py
dyconnmap/ts/ste.py
dyconnmap/ts/surrogates.py
dyconnmap/ts/teager_kaiser_energy.py
dyconnmap/ts/wald.py
dyconnmap-1.0.4.data/data/share/dyconnmap/docs/Makefile
dyconnmap-1.0.4.dist-info/LICENSE
dyconnmap-1.0.4.dist-info/METADATA
dyconnmap-1.0.4.dist-info/WHEEL
dyconnmap-1.0.4.dist-info/top_level.txt
dyconnmap-1.0.4.dist-info/RECORD
