Metadata-Version: 2.1
Name: dyconnmap
Version: 1.0.4
Summary: A dynamic connectome mapping module in Python
Home-page: https://github.com/makism/dyconnmap
Author: Avraam Marimpis, Stavros Dimitriadis
Author-email: Avraam.Marimpis@gmail.com, STIDimitriadis@gmail.com
License: BSD
Keywords: eeg fMRI meg connectivity graphs neuroimage brain
Platform: UNKNOWN
Classifier: Development Status :: 5 - Production/Stable
Classifier: Programming Language :: Python :: 3.6
Classifier: Programming Language :: Python :: 3.8
Classifier: Programming Language :: Python :: 3.9
Classifier: Intended Audience :: Science/Research
Classifier: Intended Audience :: Developers
Classifier: License :: OSI Approved
Classifier: Topic :: Software Development
Classifier: Topic :: Scientific/Engineering
Classifier: Operating System :: Microsoft :: Windows
Classifier: Operating System :: POSIX
Classifier: Operating System :: Unix
Classifier: Operating System :: MacOS
Requires-Python: ~=3.6,!=3.7,>=3.8
Requires-Dist: numpy
Requires-Dist: scipy
Requires-Dist: networkx
Requires-Dist: matplotlib
Requires-Dist: statsmodels
Requires-Dist: scikit-learn
Requires-Dist: bctpy
